ether_sql/__init__.py
ether_sql/exceptions.py
ether_sql/globals.py
ether_sql/session.py
ether_sql/settings.py
ether_sql/cli/__init__.py
ether_sql/cli/celery.py
ether_sql/cli/ether.py
ether_sql/cli/sql.py
ether_sql/constants/genesis_rewards.csv
ether_sql/constants/mainnet.py
ether_sql/constants/mainnet_dao.py
ether_sql/models/__init__.py
ether_sql/models/block_task_meta.py
ether_sql/models/blocks.py
ether_sql/models/logs.py
ether_sql/models/meta_info.py
ether_sql/models/receipts.py
ether_sql/models/state.py
ether_sql/models/state_diff.py
ether_sql/models/storage.py
ether_sql/models/storage_diff.py
ether_sql/models/traces.py
ether_sql/models/transactions.py
ether_sql/models/uncles.py
ether_sql/tasks/__init__.py
ether_sql/tasks/export.py
ether_sql/tasks/filters.py
ether_sql/tasks/scrapper.py
ether_sql/tasks/worker.py
ether_sql-0.1.3.dist-info/METADATA
ether_sql-0.1.3.dist-info/RECORD
ether_sql-0.1.3.dist-info/WHEEL
ether_sql-0.1.3.dist-info/entry_points.txt
ether_sql-0.1.3.dist-info/top_level.txt
