Metadata-Version: 2.1
Name: ether-sql
Version: 0.1.3
Summary: A python library to push ethereum blockchain data into an sql database.
Home-page: https://github.com/analyseether/ether_sql
Author: Ankit Chiplunkar
Author-email: ankit@analyseether.com
License: UNKNOWN
Keywords: ethereum
Platform: UNKNOWN
Classifier: Development Status :: 3 - Alpha
Classifier: Intended Audience :: Developers
Classifier: Natural Language :: English
Classifier: Programming Language :: Python :: 3
Classifier: Programming Language :: Python :: 3.6
Requires-Python: >=3.6, <4
Provides-Extra: linter
Provides-Extra: tester
Requires-Dist: web3 (==4.4.1)
Requires-Dist: sqlalchemy (==1.2.4)
Requires-Dist: alembic (==0.9.9)
Requires-Dist: psycopg2-binary (==2.7.4)
Requires-Dist: Click (==6.7)
Requires-Dist: Celery (==4.1.1)
Provides-Extra: linter
Requires-Dist: flake8 (==3.4.1); extra == 'linter'
Requires-Dist: isort (<5,>=4.2.15); extra == 'linter'
Provides-Extra: tester
Requires-Dist: pytest (==3.0.0); extra == 'tester'
Requires-Dist: pytest-cov (==2.2.1); extra == 'tester'
